dossier/__init__.py
dossier/dossier.py
dossier/processors.py
dossier/py.typed
agent_dossier-1.1.2.dist-info/WHEEL
agent_dossier-1.1.2.dist-info/METADATA
agent_dossier-1.1.2.dist-info/RECORD
