Metadata-Version: 2.4
Name: agent-dossier
Version: 1.1.2
Summary: A structured logging library for AI agents with session management and object unpacking
Keywords: logging,structlog,ai,agents,session-management
Author: Ricardo Decal
Author-email: Ricardo Decal <dossier-project@ricardodecal.com>
License-Expression: Apache-2.0
Classifier: Development Status :: 4 - Beta
Classifier: Intended Audience :: Developers
Classifier: License :: OSI Approved :: Apache Software License
Classifier: Programming Language :: Python :: 3
Classifier: Programming Language :: Python :: 3.13
Classifier: Topic :: Software Development :: Libraries :: Python Modules
Classifier: Topic :: System :: Logging
Requires-Dist: beartype>=0.22.5
Requires-Dist: better-exceptions>=0.3.3
Requires-Dist: rich>=14.2.0
Requires-Dist: structlog>=25.5.0
Requires-Python: >=3.13
Project-URL: Documentation, https://dossier.ricardodecal.com/
Project-URL: Homepage, https://dossier.ricardodecal.com/
Project-URL: Issues, https://github.com/crypdick/dossier/issues
Project-URL: Repository, https://github.com/crypdick/dossier
